setup.py
bin/run-pyscout-server
pyscout/__init__.py
pyscout/monitor.py
pyscout/server.py
pyscout/test_with.py
pyscout/timekeeper_plot.py
pyscout.egg-info/PKG-INFO
pyscout.egg-info/SOURCES.txt
pyscout.egg-info/dependency_links.txt
pyscout.egg-info/not-zip-safe
pyscout.egg-info/requires.txt
pyscout.egg-info/top_level.txt