Metadata-Version: 1.0
Name: pyscout
Version: 0.1.4
Summary: Realtime monitoring and benchmarking code execution
Home-page: https://github.com/agatetx/pyscout.git
Author: agatetx
Author-email: agatetx@gmail.com
License: MIT
Platform: UNKNOWN
